file_combiner/__init__.py
file_combiner/cli.py
file_combiner/combiner.py
file_combiner/combiner_template.py
llm_file_combiner-1.0.3.dist-info/METADATA
llm_file_combiner-1.0.3.dist-info/WHEEL
llm_file_combiner-1.0.3.dist-info/entry_points.txt
llm_file_combiner-1.0.3.dist-info/top_level.txt
llm_file_combiner-1.0.3.dist-info/RECORD
