Metadata-Version: 2.1
Name: llm_file_combiner
Version: 1.0.3
Summary: A tool to combine files in a folder for LLM processing
Author-email: Maximilian Winter <maximilian.winter.91@gmail.com>
Project-URL: Homepage, https://github.com/Maximilian-Winter/file_combiner
Project-URL: Bug Tracker, https://github.com/Maximilian-Winter/file_combiner/issues
Classifier: Programming Language :: Python :: 3
Classifier: License :: OSI Approved :: MIT License
Classifier: Operating System :: OS Independent
Requires-Python: >=3.6
